research_town/__init__.py
research_town/agents/__init__.py
research_town/agents/agent.py
research_town/agents/agent_manager.py
research_town/configs/__init__.py
research_town/configs/config.py
research_town/data/__init__.py
research_town/data/data.py
research_town/dbs/__init__.py
research_town/dbs/db_base.py
research_town/dbs/db_complex.py
research_town/dbs/db_log.py
research_town/dbs/db_paper.py
research_town/dbs/db_profile.py
research_town/dbs/db_progress.py
research_town/dbs/db_provider/__init__.py
research_town/dbs/db_provider/client.py
research_town/dbs/db_provider/handler.py
research_town/dbs/db_provider/local/__init__.py
research_town/dbs/db_provider/local/client.py
research_town/dbs/db_provider/registry.py
research_town/engines/__init__.py
research_town/engines/engine.py
research_town/engines/engine_base.py
research_town/envs/__init__.py
research_town/envs/env_base.py
research_town/envs/env_end.py
research_town/envs/env_proposal_writing_with_rag.py
research_town/envs/env_proposal_writing_without_rag.py
research_town/envs/env_review_writing.py
research_town/envs/env_start.py
research_town/evaluators/__init__.py
research_town/evaluators/evaluator_base.py
research_town/evaluators/evaluator_output.py
research_town/evaluators/evaluator_output_format.py
research_town/evaluators/evaluator_quality.py
research_town/utils/__init__.py
research_town/utils/agent_prompter.py
research_town/utils/error_handler.py
research_town/utils/eval_prompter.py
research_town/utils/logger.py
research_town/utils/model_prompting.py
research_town/utils/paper_collector.py
research_town/utils/profile_collector.py
research_town/utils/prompt_constructor.py
research_town/utils/retriever.py
research_town/utils/role_verifier.py
research_town/utils/sampler.py
research_town/utils/serializer.py
research_town/utils/string_mapper.py
research_town-0.0.3.dist-info/LICENSE
research_town-0.0.3.dist-info/METADATA
research_town-0.0.3.dist-info/WHEEL
research_town-0.0.3.dist-info/RECORD
