Metadata-Version: 2.1
Name: research-town
Version: 0.0.3
Summary: multi-agent environment for research community simulation
License: Apache 2.0 License
Author: Haofei Yu
Author-email: haofeiy2@illinois.edu
Requires-Python: >=3.10,<3.12
Classifier: License :: Other/Proprietary License
Classifier: Programming Language :: Python :: 3
Classifier: Programming Language :: Python :: 3.10
Classifier: Programming Language :: Python :: 3.11
Provides-Extra: backend
Provides-Extra: humaneval
Provides-Extra: researchbench
Requires-Dist: arxiv (>=2.1.0,<3.0.0)
Requires-Dist: beartype (>=0.19.0,<0.20.0)
Requires-Dist: beautifulsoup4
Requires-Dist: bert_score ; extra == "researchbench"
Requires-Dist: fastapi ; extra == "backend"
Requires-Dist: keybert
Requires-Dist: litellm (>=1.49.7,<2.0.0)
Requires-Dist: lxml
Requires-Dist: nltk ; extra == "researchbench"
Requires-Dist: numpy (<2.0.0)
Requires-Dist: pandas ; extra == "humaneval"
Requires-Dist: pydantic (>=2.5.0)
Requires-Dist: pypdf2 (>=3.0.1)
Requires-Dist: requests
Requires-Dist: rouge_score ; extra == "researchbench"
Requires-Dist: semanticscholar
Requires-Dist: socksio
Requires-Dist: termcolor (>=2.4.0,<3.0.0)
Requires-Dist: torch (>=2.2.0,<2.3.0)
Requires-Dist: tqdm
Requires-Dist: transformers (>=4.45.1,<5.0.0)
Requires-Dist: uvicorn ; extra == "backend"
Requires-Dist: voyageai ; extra == "researchbench"
